polyasite_models/__init__.py
polyasite_models/models.py
polyasite_models-0.0.1.dist-info/LICENSE
polyasite_models-0.0.1.dist-info/METADATA
polyasite_models-0.0.1.dist-info/WHEEL
polyasite_models-0.0.1.dist-info/top_level.txt
polyasite_models-0.0.1.dist-info/RECORD
