Metadata-Version: 2.1
Name: polyasite-models
Version: 0.0.1
Summary: Models for PolyASite web service
Home-page: UNKNOWN
Author: Christina J. Herrmann
Author-email: christina.herrmann@unibas.ch
License: UNKNOWN
Platform: UNKNOWN
Classifier: Programming Language :: Python :: 2.7
Classifier: License :: OSI Approved :: Apache Software License
Classifier: Topic :: Scientific/Engineering :: Bio-Informatics
Requires-Python: >=2.7
Requires-Dist: mongoengine (>=0.18.2)
